<?xml version="1.0" encoding="utf-8" standalone="yes" ?>
<T3DataStructure>
	<meta>
		<langDisable>1</langDisable>
	</meta>
	<sheets>
		<sDEF>
			<ROOT>
				<TCEforms>
					<sheetTitle>LLL:EXT:staffdirectory/Resources/Private/Language/locallang.xlf:pi_flexform.sheet_general</sheetTitle>
				</TCEforms>
				<type>array</type>
				<el>
					<settings.displayMode>
						<TCEforms>
							<label>LLL:EXT:staffdirectory/Resources/Private/Language/locallang.xlf:pi_flexform.displayMode</label>
							<onChange>reload</onChange>
							<config>
								<type>select</type>
								<renderType>selectSingle</renderType>
								<items>
									<numIndex index="0" type="array">
										<numIndex index="0"></numIndex>
										<numIndex index="1"></numIndex>
									</numIndex>
									<numIndex index="1" type="array">
										<numIndex index="0">LLL:EXT:staffdirectory/Resources/Private/Language/locallang.xlf:pi_flexform.displayMode.LIST</numIndex>
										<numIndex index="1">LIST</numIndex>
									</numIndex>
									<numIndex index="2" type="array">
										<numIndex index="0">LLL:EXT:staffdirectory/Resources/Private/Language/locallang.xlf:pi_flexform.displayMode.STAFF</numIndex>
										<numIndex index="1">STAFF</numIndex>
									</numIndex>
									<numIndex index="3" type="array">
										<numIndex index="0">LLL:EXT:staffdirectory/Resources/Private/Language/locallang.xlf:pi_flexform.displayMode.PERSONS</numIndex>
										<numIndex index="1">PERSONS</numIndex>
									</numIndex>
									<numIndex index="4" type="array">
										<numIndex index="0">LLL:EXT:staffdirectory/Resources/Private/Language/locallang.xlf:pi_flexform.displayMode.PERSON</numIndex>
										<numIndex index="1">PERSON</numIndex>
									</numIndex>
									<numIndex index="5" type="array">
										<numIndex index="0">LLL:EXT:staffdirectory/Resources/Private/Language/locallang.xlf:pi_flexform.displayMode.DIRECTORY</numIndex>
										<numIndex index="1">DIRECTORY</numIndex>
									</numIndex>
								</items>
							</config>
						</TCEforms>
					</settings.displayMode>
					<settings.staffs>
						<TCEforms>
							<label>LLL:EXT:staffdirectory/Resources/Private/Language/locallang.xlf:pi_flexform.staffs</label>
							<displayCond>
								<OR>
									<numIndex index="0"><![CDATA[FIELD:settings.displayMode:=:LIST]]></numIndex>
									<numIndex index="1"><![CDATA[FIELD:settings.displayMode:=:STAFF]]></numIndex>
									<numIndex index="2"><![CDATA[FIELD:settings.displayMode:=:DIRECTORY]]></numIndex>
								</OR>
							</displayCond>
							<config>
								<type>select</type>
								<renderType>selectMultipleSideBySide</renderType>
								<foreign_table>tx_staffdirectory_staffs</foreign_table>
								<foreign_table_where>ORDER BY tx_staffdirectory_staffs.staff_name</foreign_table_where>
								<size>8</size>
								<maxitems>99</maxitems>
								<multiple>0</multiple>
							</config>
						</TCEforms>
					</settings.staffs>
					<settings.persons>
						<TCEforms>
							<label>LLL:EXT:staffdirectory/Resources/Private/Language/locallang.xlf:pi_flexform.persons</label>
							<displayCond>
								<OR>
									<numIndex index="0"><![CDATA[FIELD:settings.displayMode:=:PERSON]]></numIndex>
									<numIndex index="1"><![CDATA[FIELD:settings.displayMode:=:PERSONS]]></numIndex>
								</OR>
							</displayCond>
							<config>
								<type>select</type>
								<renderType>selectMultipleSideBySide</renderType>
								<foreign_table>fe_users</foreign_table>
								<foreign_table_where>ORDER BY fe_users.last_name</foreign_table_where>
								<size>8</size>
								<maxitems>99</maxitems>
								<multiple>0</multiple>
							</config>
						</TCEforms>
					</settings.persons>
					<settings.layout>
						<TCEforms>
							<label>LLL:EXT:staffdirectory/Resources/Private/Language/locallang.xlf:pi_flexform.layout</label>
							<config>
								<type>select</type>
								<renderType>selectSingle</renderType>
								<items>
									<numIndex index="0" type="array">
										<numIndex index="0">LLL:EXT:staffdirectory/Resources/Private/Language/locallang.xlf:pi_flexform.layout.Normal</numIndex>
										<numIndex index="1">Normal</numIndex>
									</numIndex>
									<numIndex index="1" type="array">
										<numIndex index="0">LLL:EXT:staffdirectory/Resources/Private/Language/locallang.xlf:pi_flexform.layout.Condensed</numIndex>
										<numIndex index="1">Condensed</numIndex>
									</numIndex>
								</items>
							</config>
						</TCEforms>
					</settings.layout>
				</el>
			</ROOT>
		</sDEF>
	</sheets>
</T3DataStructure>